fastql_packages/__init__.py
fastql_packages/auth_model.py
fastql_packages/lib.py
fastql_packages/main.py
fastql_packages/modules.py
fastql_packages/packages.py
fastql_packages/security.py
fastql_packages/templates/auth.fastql
fastql_packages/templates/config-app.fastql
fastql_packages/templates/config-db.fastql
fastql_packages/templates/migration-table.fastql
fastql_packages/templates/migration.fastql
fastql_packages/templates/model.fastql
fastql_packages/templates/mutation-schema.fastql
fastql_packages/templates/mutation.fastql
fastql_packages/templates/serialize.fastql
fastql_packages-0.1.7.dist-info/entry_points.txt
fastql_packages-0.1.7.dist-info/WHEEL
fastql_packages-0.1.7.dist-info/METADATA
fastql_packages-0.1.7.dist-info/RECORD
