Metadata-Version: 2.1
Name: fastql-packages
Version: 0.1.7
Summary: 
Author: Muhammad Abdurrahman
Author-email: rachman.sd@gmail.com
Requires-Python: >=3.6,<4
Classifier: Programming Language :: Python :: 3
Classifier: Programming Language :: Python :: 3.6
Classifier: Programming Language :: Python :: 3.7
Classifier: Programming Language :: Python :: 3.8
Classifier: Programming Language :: Python :: 3.9
Requires-Dist: Jinja2 (>=3.0.0,<4.0.0)
Requires-Dist: click (>=7.1.2,<8.0.0)
Requires-Dist: colorama (>=0.4.4,<0.5.0)
Requires-Dist: fastapi (>=0.65.1,<0.66.0)
Requires-Dist: graphene (>=3.0b5)
Requires-Dist: graphene-pydantic (>=0.2.0,<0.3.0)
Requires-Dist: inflect (>=5.3.0,<6.0.0)
Requires-Dist: orator (>=0.9.9,<0.10.0)
Requires-Dist: passlib (>=1.7.4,<2.0.0)
Requires-Dist: python-dotenv (>=0.17.1,<0.18.0)
Requires-Dist: requests (>=2.25.1,<3.0.0)
Requires-Dist: uvicorn (>=0.13.4,<0.14.0)
